setup.py
xuino/__init__.py
xuino/__main__.py
xuino/dependencies.json
xuino/xuino.py
xuino.egg-info/PKG-INFO
xuino.egg-info/SOURCES.txt
xuino.egg-info/dependency_links.txt
xuino.egg-info/entry_points.txt
xuino.egg-info/top_level.txt
xuino/makefiles/Library.mk
xuino/makefiles/Project.mk
xuino/makefiles/libraries/Libraries.md