Metadata-Version: 1.1
Name: xuino
Version: 0.1.1
Summary: Command-line Arduino toolkit.
Home-page: https://github.com/michaelsproul/xuino
Author: Michael Sproul
Author-email: micsproul@gmail.com
License: GPLv3
Keywords: arduino build compile avr tool command-line
Platform: UNKNOWN
Classifier: Development Status :: 3 - Alpha
Classifier: Intended Audience :: Developers
Classifier: Intended Audience :: Education
Classifier: Environment :: Console
Classifier: License :: OSI Approved :: GNU General Public License v3 or later (GPLv3+)
Classifier: Programming Language :: Python :: 3
Classifier: Topic :: Software Development :: Build Tools
Classifier: Topic :: Software Development :: Embedded Systems
